{
    "channel_description": "A categoria Infantil contém vídeos para entreter os Treinadores mais novos. As crianças podem se divertir com músicas para cantar junto, ouvir músicas infantis populares e muito mais!",
    "stunt_channel": true,
    "channel_name": "Pokémon Kids TV",
    "media": [
        {
            "episode": "",
            "description": "Ouça esta melodia familiar: é uma daquelas músicas conhecidas ao redor do mundo, mas que possuem vários nomes diferentes como “Valsa das Pulgas”, “Flea Waltz”, “La Chocolatera” e “Flohwalzer”.",
            "is_country_whitelist": false,
            "title": "Valsa das Pulgas / La Chocolatera / Flohwalzer",
            "season": "",
            "images": {
                "small": "https://assets.pokemon.com/assets/cms2/img/watch-pokemon-tv/original/pokemon-kids-tv/flea-waltz-01-180x103.jpg",
                "large": "https://assets.pokemon.com/assets/cms2/img/watch-pokemon-tv/original/pokemon-kids-tv/flea-waltz-01.jpg",
                "medium": "https://assets.pokemon.com/assets/cms2/img/watch-pokemon-tv/original/pokemon-kids-tv/flea-waltz-01-360x206.jpg"
            },
            "skimming_thumbnail_url_base": "https://s2.content.video.llnw.net/images-prod/SVMzbX9UT2cihInCxduo4Y/jJVNvkMNRv8q1zaS7v2Bno/skim/",
            "is_new": false,
            "country_codes": [
                "JP",
                "HK",
                "VN",
                "TH",
                "NP",
                "BD",
                "ID",
                "BN",
                "KH",
                "KP",
                "KR",
                "WS",
                "SG",
                "MY",
                "IN",
                "MN",
                "MM",
                "MO",
                "LA",
                "PH",
                "PK",
                "AF",
                "LK",
                "PG",
                "CN",
                "TW"
            ],
            "offline_url": "https://s2.content.video.llnw.net/smedia/4953336d7f544f678a12270b176ea386/33/8vgo_-yyIl3NMbi3HMl3Hmvqh-NEglXpMPaK4Z5-c/flea-waltz-bpo.mp4",
            "last_modified": 1629821826,
            "stream_url": "https://s2.content.video.llnw.net/smedia/4953336d7f544f678a12270b176ea386/e5/-GEiFjs4VqssrqPJ6D-1-dH13oYpDOoxOIeNBcYBY/flea-waltz-bpo-e2386529e93607efe0023b9f7141cd542b96f9bf.m3u8",
            "captions": "",
            "id": "8c954dbe430d46ffab5cda4bbbf6067a",
            "size": 582066952
        },
        {
            "episode": "",
            "description": "Siga Mewtwo enquanto ele sobrevoa paisagens, montanhas e mares de tirar o fôlego. Este vídeo é um banquete para os olhos e ouvidos! Música: “Pompa e Circunstância” antecedida por trechos de “Orfeu no Inferno”.",
            "is_country_whitelist": false,
            "title": "O voo de Mewtwo",
            "season": "",
            "images": {
                "small": "https://assets.pokemon.com/assets/cms2/img/watch-pokemon-tv/original/pokemon-kids-tv/flight-of-mewtwo-01-180x103.jpg",
                "large": "https://assets.pokemon.com/assets/cms2/img/watch-pokemon-tv/original/pokemon-kids-tv/flight-of-mewtwo-01.jpg",
                "medium": "https://assets.pokemon.com/assets/cms2/img/watch-pokemon-tv/original/pokemon-kids-tv/flight-of-mewtwo-01-360x206.jpg"
            },
            "skimming_thumbnail_url_base": "https://s2.content.video.llnw.net/images-prod/SVMzbX9UT2cihInCxduo4Y/R1pgVttiSlIqgOm-UOjNHY/skim/",
            "is_new": false,
            "country_codes": [
                "JP",
                "HK",
                "VN",
                "TH",
                "NP",
                "BD",
                "ID",
                "BN",
                "KH",
                "KP",
                "KR",
                "WS",
                "SG",
                "MY",
                "IN",
                "MN",
                "MM",
                "MO",
                "LA",
                "PH",
                "PK",
                "AF",
                "LK",
                "PG",
                "CN",
                "TW"
            ],
            "offline_url": "https://s2.content.video.llnw.net/smedia/4953336d7f544f678a12270b176ea386/vB/6TyV9VXGMcOq-FdY_VtA2dcGcbV0zNOBrO3XMtXSE/flight-of-mewtwo-bpo.mp4",
            "last_modified": 1629821826,
            "stream_url": "https://s2.content.video.llnw.net/smedia/4953336d7f544f678a12270b176ea386/34/y_eZ2IMbCtSxvQ6voa2hMWwez_8JTtuI_mMn6UrTw/flight-of-mewtwo-bpo-a478cde58903f918a880aa33177f2434524c6c26.m3u8",
            "captions": "",
            "id": "475a6056db624a52aa03a6f943a33476",
            "size": 590229214
        },
        {
            "episode": "",
            "description": "Parece que Pokémon não se importam de marchar se a música for divertida!",
            "is_country_whitelist": false,
            "title": "A grande marcha Pokémon",
            "season": "",
            "images": {
                "small": "https://assets.pokemon.com/assets/cms2/img/watch-pokemon-tv/original/pokemon-kids-tv/great-march-of-pokemon-01-180x103.jpg",
                "large": "https://assets.pokemon.com/assets/cms2/img/watch-pokemon-tv/original/pokemon-kids-tv/great-march-of-pokemon-01.jpg",
                "medium": "https://assets.pokemon.com/assets/cms2/img/watch-pokemon-tv/original/pokemon-kids-tv/great-march-of-pokemon-01-360x206.jpg"
            },
            "skimming_thumbnail_url_base": "https://s2.content.video.llnw.net/images-prod/SVMzbX9UT2cihInCxduo4Y/mZHXZsRmRfUlMUsU4KUYQw/skim/",
            "is_new": false,
            "country_codes": [
                "JP",
                "HK",
                "VN",
                "TH",
                "NP",
                "BD",
                "ID",
                "BN",
                "KH",
                "KP",
                "KR",
                "WS",
                "SG",
                "MY",
                "IN",
                "MN",
                "MM",
                "MO",
                "LA",
                "PH",
                "PK",
                "AF",
                "LK",
                "PG",
                "CN",
                "TW"
            ],
            "offline_url": "https://s2.content.video.llnw.net/smedia/4953336d7f544f678a12270b176ea386/E_/2kd7qugPMHc7Zd2MAY0rHDmOs9sqVG7CxMLr0U7W0/great-march-of-pok--mon-bpo.mp4",
            "last_modified": 1629821826,
            "stream_url": "https://s2.content.video.llnw.net/smedia/4953336d7f544f678a12270b176ea386/Ku/VO1Wruv-Gu8mlqlDu4EdQisvoFQm9BlYgnFty8JA8/great-march-of-pok--mon-bpo-2ff27a52712e05f2f16630352207e0b8a978e3c0.m3u8",
            "captions": "",
            "id": "9991d766c46645f594c52c538294610c",
            "size": 923696272
        },
        {
            "episode": "",
            "description": "Seus parceiros Pikachu e Eevee têm feito você cantar, cantar e cantar, mas não se esqueça de dançar também!",
            "is_country_whitelist": false,
            "title": "Eu amo Pikachu E Eevee",
            "season": "",
            "images": {
                "small": "https://assets.pokemon.com/assets/cms2/img/watch-pokemon-tv/original/pokemon-kids-tv/i-love-you-pikachu-and-eevee-01-180x103.jpg",
                "large": "https://assets.pokemon.com/assets/cms2/img/watch-pokemon-tv/original/pokemon-kids-tv/i-love-you-pikachu-and-eevee-01.jpg",
                "medium": "https://assets.pokemon.com/assets/cms2/img/watch-pokemon-tv/original/pokemon-kids-tv/i-love-you-pikachu-and-eevee-01-360x206.jpg"
            },
            "skimming_thumbnail_url_base": "https://s2.content.video.llnw.net/images-prod/SVMzbX9UT2cihInCxduo4Y/HmQXz6GiS-stOOrtufzbF8/skim/",
            "is_new": false,
            "country_codes": [
                "JP",
                "HK",
                "VN",
                "TH",
                "NP",
                "BD",
                "ID",
                "BN",
                "KH",
                "KP",
                "KR",
                "WS",
                "SG",
                "MY",
                "IN",
                "MN",
                "MM",
                "MO",
                "LA",
                "PH",
                "PK",
                "AF",
                "LK",
                "PG",
                "CN",
                "TW"
            ],
            "offline_url": "https://s2.content.video.llnw.net/smedia/4953336d7f544f678a12270b176ea386/On/8DTo9yfzt2KbSk6wkEqlbFRuM9N6hWsCBoqeDKd6M/i-love-pikachu-and-eevee--dance-version--bpo.mp4",
            "last_modified": 1629821826,
            "stream_url": "https://s2.content.video.llnw.net/smedia/4953336d7f544f678a12270b176ea386/OY/sKUueByn6QHqyH6K3r11hGdxKQlwIDOn2TKLCCRaQ/i-love-pikachu-and-eevee--dance-version--bpo-695bf0414407e19a95a180f83a65bb32c95edb59.m3u8",
            "captions": "",
            "id": "1e6417cfa1a24bebb4e3abb6e7f36c5f",
            "size": 430155802
        },
        {
            "episode": "",
            "description": "Será que esta música peculiar e esta apresentação extravagante de Pokémon vão encantar você e te ajudar a dormir? Você pode ter certeza que estes Pokémon pequeninos vão ficar com bastante sono!",
            "is_country_whitelist": false,
            "title": "Canção de ninar Pokémon",
            "season": "",
            "images": {
                "small": "https://assets.pokemon.com/assets/cms2/img/watch-pokemon-tv/original/pokemon-kids-tv/pokemon-lulling-lullaby-01-180x103.jpg",
                "large": "https://assets.pokemon.com/assets/cms2/img/watch-pokemon-tv/original/pokemon-kids-tv/pokemon-lulling-lullaby-01.jpg",
                "medium": "https://assets.pokemon.com/assets/cms2/img/watch-pokemon-tv/original/pokemon-kids-tv/pokemon-lulling-lullaby-01-360x206.jpg"
            },
            "skimming_thumbnail_url_base": "https://s2.content.video.llnw.net/images-prod/SVMzbX9UT2cihInCxduo4Y/2pV_xau_R90g5EiH47Qmlg/skim/",
            "is_new": false,
            "country_codes": [
                "JP",
                "HK",
                "VN",
                "TH",
                "NP",
                "BD",
                "ID",
                "BN",
                "KH",
                "KP",
                "KR",
                "WS",
                "SG",
                "MY",
                "IN",
                "MN",
                "MM",
                "MO",
                "LA",
                "PH",
                "PK",
                "AF",
                "LK",
                "PG",
                "CN",
                "TW"
            ],
            "offline_url": "https://s2.content.video.llnw.net/smedia/4953336d7f544f678a12270b176ea386/MU/ciiNcLUs5Bodmu3osXILlWOeSQHK1D3JRqUZejjYg/poke--mon-lulling-lullaby-bpo.mp4",
            "last_modified": 1629821826,
            "stream_url": "https://s2.content.video.llnw.net/smedia/4953336d7f544f678a12270b176ea386/sA/oCUO9egP5OngWqv_ZrCZGO_VtLtT1ljdzdIhNWcZU/poke--mon-lulling-lullaby-bpo-7d900e178a017947891e83025bbdb763bfbe6551.m3u8",
            "captions": "",
            "id": "da957fc5abbf47dd8391221f8ed09a58",
            "size": 866791905
        },
        {
            "episode": "",
            "description": "Sinta o ritmo da música e acompanhe o vídeo para ver se seu Pokémon favorito está dentro de uma das Poké Bolas rolando!",
            "is_country_whitelist": false,
            "title": "Poké Bolas rolando",
            "season": "",
            "images": {
                "small": "https://assets.pokemon.com/assets/cms2/img/watch-pokemon-tv/original/pokemon-kids-tv/rolling-poke-balls-1-01-180x103.jpg",
                "large": "https://assets.pokemon.com/assets/cms2/img/watch-pokemon-tv/original/pokemon-kids-tv/rolling-poke-balls-1-01.jpg",
                "medium": "https://assets.pokemon.com/assets/cms2/img/watch-pokemon-tv/original/pokemon-kids-tv/rolling-poke-balls-1-01-360x206.jpg"
            },
            "skimming_thumbnail_url_base": "https://s2.content.video.llnw.net/images-prod/SVMzbX9UT2cihInCxduo4Y/sauo0dxbThAlBrFxSPIeK0/skim/",
            "is_new": false,
            "country_codes": [
                "JP",
                "HK",
                "VN",
                "TH",
                "NP",
                "BD",
                "ID",
                "BN",
                "KH",
                "KP",
                "KR",
                "WS",
                "SG",
                "MY",
                "IN",
                "MN",
                "MM",
                "MO",
                "LA",
                "PH",
                "PK",
                "AF",
                "LK",
                "PG",
                "CN",
                "TW"
            ],
            "offline_url": "https://s2.content.video.llnw.net/smedia/4953336d7f544f678a12270b176ea386/nT/4pEU_5roSSv2EqUMMua4-Qm9_ZxIj_NLk0iXRWy4I/rolling-poke---balls-1-bpo.mp4",
            "last_modified": 1629821826,
            "stream_url": "https://s2.content.video.llnw.net/smedia/4953336d7f544f678a12270b176ea386/OB/cozIng4NOpGcw8qEPpLoPKiR-UieTYHr7iVFkHZu0/rolling-poke---balls-1-bpo-8c12ccb8282654cfc762ef9efe6d2726622146ff.m3u8",
            "captions": "",
            "id": "b1aba8d1dc5b4e10941ac5c523c878ad",
            "size": 934344396
        },
        {
            "episode": "",
            "description": "Sinta o ritmo da música e acompanhe o vídeo para ver se seu Pokémon favorito está dentro de uma das Poké Bolas rolando!",
            "is_country_whitelist": false,
            "title": "Poké Bolas rolando 2",
            "season": "",
            "images": {
                "small": "https://assets.pokemon.com/assets/cms2/img/watch-pokemon-tv/original/pokemon-kids-tv/rolling-poke-balls-2-01-180x103.jpg",
                "large": "https://assets.pokemon.com/assets/cms2/img/watch-pokemon-tv/original/pokemon-kids-tv/rolling-poke-balls-2-01.jpg",
                "medium": "https://assets.pokemon.com/assets/cms2/img/watch-pokemon-tv/original/pokemon-kids-tv/rolling-poke-balls-2-01-360x206.jpg"
            },
            "skimming_thumbnail_url_base": "https://s2.content.video.llnw.net/images-prod/SVMzbX9UT2cihInCxduo4Y/1rKeTLaeTuMh-UHsbN-QnU/skim/",
            "is_new": false,
            "country_codes": [
                "JP",
                "HK",
                "VN",
                "TH",
                "NP",
                "BD",
                "ID",
                "BN",
                "KH",
                "KP",
                "KR",
                "WS",
                "SG",
                "MY",
                "IN",
                "MN",
                "MM",
                "MO",
                "LA",
                "PH",
                "PK",
                "AF",
                "LK",
                "PG",
                "CN",
                "TW"
            ],
            "offline_url": "https://s2.content.video.llnw.net/smedia/4953336d7f544f678a12270b176ea386/w9/FYKw_GxGgTbcOX9FmAGdhbdANeQ46HH-cJ9IqBjjQ/rolling-poke---balls-2-bpo.mp4",
            "last_modified": 1629821826,
            "stream_url": "https://s2.content.video.llnw.net/smedia/4953336d7f544f678a12270b176ea386/Cv/DenG1uWGmFMZKBUQpOYWmb7ZBhDmOUbZm7CkHUVh8/rolling-poke---balls-2-bpo-d727c740d98a88dbd29e5ce32b88567c37e62c72.m3u8",
            "captions": "",
            "id": "d6b29e4cb69e4ee387e507b1b37e4275",
            "size": 925526038
        },
        {
            "episode": "",
            "description": "Sinta o ritmo da música e acompanhe o vídeo para ver se seu Pokémon favorito está dentro de uma das Poké Bolas rolando!",
            "is_country_whitelist": false,
            "title": "Poké Bolas rolando 3",
            "season": "",
            "images": {
                "small": "https://assets.pokemon.com/assets/cms2/img/watch-pokemon-tv/original/pokemon-kids-tv/rolling-poke-balls-3-01-180x103.jpg",
                "large": "https://assets.pokemon.com/assets/cms2/img/watch-pokemon-tv/original/pokemon-kids-tv/rolling-poke-balls-3-01.jpg",
                "medium": "https://assets.pokemon.com/assets/cms2/img/watch-pokemon-tv/original/pokemon-kids-tv/rolling-poke-balls-3-01-360x206.jpg"
            },
            "skimming_thumbnail_url_base": "https://s2.content.video.llnw.net/images-prod/SVMzbX9UT2cihInCxduo4Y/jGvvt_43SLsppw8RN_N_ps/skim/",
            "is_new": false,
            "country_codes": [
                "JP",
                "HK",
                "VN",
                "TH",
                "NP",
                "BD",
                "ID",
                "BN",
                "KH",
                "KP",
                "KR",
                "WS",
                "SG",
                "MY",
                "IN",
                "MN",
                "MM",
                "MO",
                "LA",
                "PH",
                "PK",
                "AF",
                "LK",
                "PG",
                "CN",
                "TW"
            ],
            "offline_url": "https://s2.content.video.llnw.net/smedia/4953336d7f544f678a12270b176ea386/_Q/F5PBFTDnMcKtQeGHokkpZwFOtpKa4WRHMf_18ccZQ/rolling-poke---balls-3-bpo.mp4",
            "last_modified": 1629821826,
            "stream_url": "https://s2.content.video.llnw.net/smedia/4953336d7f544f678a12270b176ea386/cg/utcp_ubGEv_kHMjdhOg1CkdVXMjs1S7hjCPjW-uLQ/rolling-poke---balls-3-bpo-b4bbbf15923cdeaa10694803e1d17b996e6bb660.m3u8",
            "captions": "",
            "id": "8c6befb7fe3748bba69c3c44dfcdfe9b",
            "size": 932770970
        },
        {
            "episode": "",
            "description": "Sinta o ritmo da música e acompanhe o vídeo para ver se seu Pokémon favorito está dentro de uma das Poké Bolas rolando!",
            "is_country_whitelist": false,
            "title": "Poké Bolas rolando 4",
            "season": "",
            "images": {
                "small": "https://assets.pokemon.com/assets/cms2/img/watch-pokemon-tv/original/pokemon-kids-tv/rolling-poke-balls-4-01-180x103.jpg",
                "large": "https://assets.pokemon.com/assets/cms2/img/watch-pokemon-tv/original/pokemon-kids-tv/rolling-poke-balls-4-01.jpg",
                "medium": "https://assets.pokemon.com/assets/cms2/img/watch-pokemon-tv/original/pokemon-kids-tv/rolling-poke-balls-4-01-360x206.jpg"
            },
            "skimming_thumbnail_url_base": "https://s2.content.video.llnw.net/images-prod/SVMzbX9UT2cihInCxduo4Y/LBn9SB9TTi0rSI-Wr1UhVU/skim/",
            "is_new": false,
            "country_codes": [
                "JP",
                "HK",
                "VN",
                "TH",
                "NP",
                "BD",
                "ID",
                "BN",
                "KH",
                "KP",
                "KR",
                "WS",
                "SG",
                "MY",
                "IN",
                "MN",
                "MM",
                "MO",
                "LA",
                "PH",
                "PK",
                "AF",
                "LK",
                "PG",
                "CN",
                "TW"
            ],
            "offline_url": "https://s2.content.video.llnw.net/smedia/4953336d7f544f678a12270b176ea386/ke/RlcdmLe3W85W7K2aIdnNWKCYC5TgciKZywwR3ZVzU/rolling-poke---balls-4-bpo.mp4",
            "last_modified": 1629821826,
            "stream_url": "https://s2.content.video.llnw.net/smedia/4953336d7f544f678a12270b176ea386/_6/Z-Q179Y8zsC5KI9FcaW5LmTdD9kuitPfqihugf89k/rolling-poke---balls-4-bpo-0a129d80947b25f86d62ccc294db0ebf86bfb9ee.m3u8",
            "captions": "",
            "id": "2c19fd481f534e2dad223e5abd548555",
            "size": 932963393
        },
        {
            "episode": "",
            "description": "Veja Pikachu e Pelipper procurando e encontrando seus companheiros Pokémon!",
            "is_country_whitelist": false,
            "title": "Encontre o Pokémon",
            "season": "",
            "images": {
                "small": "https://assets.pokemon.com/assets/cms2/img/watch-pokemon-tv/original/pokemon-kids-tv/spot-the-pokemon-01-180x103.jpg",
                "large": "https://assets.pokemon.com/assets/cms2/img/watch-pokemon-tv/original/pokemon-kids-tv/spot-the-pokemon-01.jpg",
                "medium": "https://assets.pokemon.com/assets/cms2/img/watch-pokemon-tv/original/pokemon-kids-tv/spot-the-pokemon-01-360x206.jpg"
            },
            "skimming_thumbnail_url_base": "https://s2.content.video.llnw.net/images-prod/SVMzbX9UT2cihInCxduo4Y/gijdHSIFQewrdLUBslgWQk/skim/",
            "is_new": false,
            "country_codes": [
                "JP",
                "HK",
                "VN",
                "TH",
                "NP",
                "BD",
                "ID",
                "BN",
                "KH",
                "KP",
                "KR",
                "WS",
                "SG",
                "MY",
                "IN",
                "MN",
                "MM",
                "MO",
                "LA",
                "PH",
                "PK",
                "AF",
                "LK",
                "PG",
                "CN",
                "TW"
            ],
            "offline_url": "https://s2.content.video.llnw.net/smedia/4953336d7f544f678a12270b176ea386/7m/tCMoJNtFEmq8m_Jb1-mIN_Oi_kpUvx_alXQ8jU1qE/spot-the-poke--mon-bpo.mp4",
            "last_modified": 1629821826,
            "stream_url": "https://s2.content.video.llnw.net/smedia/4953336d7f544f678a12270b176ea386/FQ/5pVFPkzh-Qk1LNGvb2S8AF3y4e2w36R_pG8JHPTxg/spot-the-poke--mon-bpo-4a70deb2b9dd01c3503f65f4e1de2ad944512c8e.m3u8",
            "captions": "",
            "id": "8228dd1d220541ecadd2d406c9605909",
            "size": 703854585
        },
        {
            "episode": "",
            "description": "Ande neste ônibus com Pikachu e seus amigos em uma viagem pela cidade! Cante junto e divirta-se!",
            "is_country_whitelist": false,
            "title": "As Rodas do Ônibus",
            "season": "",
            "images": {
                "small": "https://assets.pokemon.com/assets/cms2/img/watch-pokemon-tv/original/pokemon-kids-tv/the-wheels-on-the-bus-01-180x103.jpg",
                "large": "https://assets.pokemon.com/assets/cms2/img/watch-pokemon-tv/original/pokemon-kids-tv/the-wheels-on-the-bus-01.jpg",
                "medium": "https://assets.pokemon.com/assets/cms2/img/watch-pokemon-tv/original/pokemon-kids-tv/the-wheels-on-the-bus-01-360x206.jpg"
            },
            "skimming_thumbnail_url_base": "https://s2.content.video.llnw.net/images-prod/SVMzbX9UT2cihInCxduo4Y/L2Je-6hVTgggHdWHi-3r44/skim/",
            "is_new": false,
            "country_codes": [
                "JP",
                "HK",
                "VN",
                "TH",
                "NP",
                "BD",
                "ID",
                "BN",
                "KH",
                "KP",
                "KR",
                "WS",
                "SG",
                "MY",
                "IN",
                "MN",
                "MM",
                "MO",
                "LA",
                "PH",
                "PK",
                "AF",
                "LK",
                "PG",
                "CN",
                "TW"
            ],
            "offline_url": "https://s2.content.video.llnw.net/smedia/4953336d7f544f678a12270b176ea386/jv/x6vCwNDvxvQy6pBmjZUaaLB4TizEsIRAotJSwLOMU/the-wheels-on-the-bus-bpo.mp4",
            "last_modified": 1629821826,
            "stream_url": "https://s2.content.video.llnw.net/smedia/4953336d7f544f678a12270b176ea386/Zw/EUgM9QhUMNyem97tFiSdE8HmfgHMFzNRT1uRVkoIM/the-wheels-on-the-bus-bpo-77b50e68cf9afb829cbfc145868d1987c8bc5610.m3u8",
            "captions": "",
            "id": "2f625efba8554e088077561e2fb7af8e",
            "size": 476588778
        },
        {
            "episode": "",
            "description": "Veja as estrelas do mundo de Pokémon brilhando no céu noturno! Cante junto e aproveite este momento na companhia de todos!",
            "is_country_whitelist": false,
            "title": "Brilha, Brilha Estrelinha",
            "season": "",
            "images": {
                "small": "https://assets.pokemon.com/assets/cms2/img/watch-pokemon-tv/original/pokemon-kids-tv/twinkle-twinkle-little-star-01-180x103.jpg",
                "large": "https://assets.pokemon.com/assets/cms2/img/watch-pokemon-tv/original/pokemon-kids-tv/twinkle-twinkle-little-star-01.jpg",
                "medium": "https://assets.pokemon.com/assets/cms2/img/watch-pokemon-tv/original/pokemon-kids-tv/twinkle-twinkle-little-star-01-360x206.jpg"
            },
            "skimming_thumbnail_url_base": "https://s2.content.video.llnw.net/images-prod/SVMzbX9UT2cihInCxduo4Y/xhULYNC5R1EoQVaHP5lbTo/skim/",
            "is_new": false,
            "country_codes": [
                "JP",
                "HK",
                "VN",
                "TH",
                "NP",
                "BD",
                "ID",
                "BN",
                "KH",
                "KP",
                "KR",
                "WS",
                "SG",
                "MY",
                "IN",
                "MN",
                "MM",
                "MO",
                "LA",
                "PH",
                "PK",
                "AF",
                "LK",
                "PG",
                "CN",
                "TW"
            ],
            "offline_url": "https://s2.content.video.llnw.net/smedia/4953336d7f544f678a12270b176ea386/Gx/pyxEilv31mZVobim5u38nW6bs3Q91lJYd_i-RtN-w/twinkle-twinkle-little-star-bpo.mp4",
            "last_modified": 1629821826,
            "stream_url": "https://s2.content.video.llnw.net/smedia/4953336d7f544f678a12270b176ea386/U_/in4epPM4D_H0yyFHL-xOWYFmOWHWBsPrS-RBp1jTs/twinkle-twinkle-little-star-bpo-e63853c12fea8c0aefd6534bd31f7303790a8b1d.m3u8",
            "captions": "",
            "id": "c6150b60d0b94751a1055a1cfe656d3a",
            "size": 359402150
        }
    ],
    "channel_creation_date": 1629821828,
    "whats_new_order": null,
    "watch_now_order": 5,
    "channel_id": "pokemon-kids-tv",
    "channel_images": {
        "dashboard_image_1125_1500": "https://assets.pokemon.com/assets/cms2/img/watch-pokemon-tv/pokemon-tv-app/pokemon-kids-tv/pokemon-kids-tv-1125x1500.jpg",
        "spotlight_image_960_1277": "",
        "spotlight_image_2048_1152": "",
        "spotlight_image_1660_940": "https://assets.pokemon.com/assets/cms2/img/watch-pokemon-tv/pokemon-tv-app/pokemon-kids-tv/pokemon-kids-tv-1660x940.jpg",
        "spotlight_image_2732_940": "https://assets.pokemon.com/assets/cms2/img/watch-pokemon-tv/pokemon-tv-app/pokemon-kids-tv/pokemon-kids-tv-2732x940.jpg"
    },
    "channel_update_date": 1633616393,
    "media_type": "junior",
    "channel_status": ""
}
